pe_signgen/__init__.py
pe_signgen/cache.py
pe_signgen/cli.py
pe_signgen/constants.py
pe_signgen/exceptions.py
pe_signgen/formats.py
pe_signgen/git.py
pe_signgen/http.py
pe_signgen/logging_config.py
pe_signgen/models.py
pe_signgen/pe_parsing.py
pe_signgen/pipeline.py
pe_signgen/progress.py
pe_signgen/signatures.py
pe_signgen/symbol_server.py
pe_signgen/symbols.py
pe_signgen/versioning.py
pe_signgen/winbindex.py
pe_signgen-0.3.1.dist-info/licenses/LICENSE
pe_signgen-0.3.1.dist-info/METADATA
pe_signgen-0.3.1.dist-info/WHEEL
pe_signgen-0.3.1.dist-info/entry_points.txt
pe_signgen-0.3.1.dist-info/top_level.txt
pe_signgen-0.3.1.dist-info/RECORD
