Metadata-Version: 2.4
Name: pe-signgen
Version: 0.3.1
Summary: Generate unique byte signatures for Windows PE functions
License: MIT
Project-URL: Homepage, https://github.com/forentfraps/pe-signgen
Project-URL: Documentation, https://github.com/forentfraps/pe-signgen#readme
Project-URL: Repository, https://github.com/forentfraps/pe-signgen
Project-URL: Issues, https://github.com/forentfraps/pe-signgen/issues
Keywords: windows,pe,signatures,pdb,symbols,reverse-engineering
Requires-Python: >=3.10
License-File: LICENSE
Requires-Dist: pefile>=2023.2.7
Requires-Dist: requests>=2.28.0
Requires-Dist: winpdb-rs>=0.1.0
Provides-Extra: native
Requires-Dist: pdb_native; extra == "native"
Provides-Extra: dev
Requires-Dist: pytest>=7.0; extra == "dev"
Requires-Dist: pytest-cov>=4.0; extra == "dev"
Requires-Dist: mypy>=1.0; extra == "dev"
Requires-Dist: black>=23.0; extra == "dev"
Requires-Dist: ruff>=0.1.0; extra == "dev"
Dynamic: license-file
